smitfit/__init__.py
smitfit/__version__.py
smitfit/_version.py
smitfit/composite_expr.py
smitfit/curve_fit.py
smitfit/error.py
smitfit/expr.py
smitfit/function.py
smitfit/lmfit.py
smitfit/loss.py
smitfit/markov.py
smitfit/minimize.py
smitfit/model.py
smitfit/operator.py
smitfit/parameter.py
smitfit/reduce.py
smitfit/result.py
smitfit/root.py
smitfit/symbol.py
smitfit/typing.py
smitfit/utils.py
smitfit-0.1.1.dist-info/METADATA
smitfit-0.1.1.dist-info/WHEEL
smitfit-0.1.1.dist-info/licenses/LICENSE
smitfit-0.1.1.dist-info/RECORD
