Metadata-Version: 2.4
Name: smitfit
Version: 0.1.1
Summary: Symbolic Model Inference Toolkit
Project-URL: Source, https://github.com/Jhsmitfit/smitfit/
Author-email: Jochem smitfit <jhsmitfit@gmail.com>
License: MIT License
License-File: LICENSE
Classifier: Development Status :: 2 - Pre-Alpha
Classifier: Intended Audience :: Science/Research
Classifier: Programming Language :: Python :: 3.10
Requires-Python: >=3.10
Requires-Dist: numpy
Requires-Dist: scipy
Requires-Dist: sympy>1.13.0
Requires-Dist: toposort
Provides-Extra: test
Requires-Dist: pytest>=7.2.0; extra == 'test'
